{
  "data": {
    "first":[{
      "username": "11001",
      "password": "123",
      "token": "eyJhbGciOiJIUzI1NiIsInR5cCI6IkpXVCJ9.eyJzdWIiOiIxMjM0NTY3ODkwIiwibmFtZSI6ImZpcnN0IiwiaWF0IjoxNTE2MjM5MDIyfQ.JjbgD5XBSJBHAUudu_FrsG_1chGipuXMVlrQsMVN9tE",
      "identity": "collegeLeader"
    },{
      "username": "11002",
      "password": "123",
      "token": "112",
      "identity": "collegeLeader"
    }],
    "second":[{
      "username": "21001",
      "password": "123",
      "token": "121",
      "identity": "dean"
    },{
      "username": "21002",
      "password": "123",
      "token": "122",
      "identity": "dean"
    }],
    "third":[{
      "username": "31001",
      "password": "123",
      "token": "131",
      "identity": "inspector"
    },{
      "username": "31002",
      "password": "123",
      "token": "132",
      "identity": "inspector"
    }],
    "fourth":[{
      "username": "41001",
      "password": "123",
      "token": "141",
      "identity": "secretary"
    },{
      "username": "41002",
      "password": "123",
      "token": "142",
      "identity": "secretary"
    }],
    "fifth":[{
      "username": "51001",
      "password": "123",
      "token": "151",
      "identity": "teacher"
    },{
      "username": "51002",
      "password": "123",
      "token": "152",
      "identity": "teacher"
    }],
    "student":[{
      "username": "61001",
      "password": "123",
      "token": "161",
      "identity": "student"
    },{
      "username": "61002",
      "password": "123",
      "token": "162",
      "identity": "student"
    }],
    "admin":[{
      "username": "admin",
      "password": "admin",
      "token": "admin",
      "identity": "admin"
    }]
  }
}
